Metadata-Version: 2.1
Name: TaiwanTrainVerificationCode2text
Version: 1.0.17
Summary: Taiwan Train VerificationCode2text
Home-page: https://github.com/linsamtw
Author: linsam
Author-email: samlin266118@gmail.com
License: UNKNOWN
Project-URL: Source, https://github.com/linsamtw/TaiwanTrainVerificationCode2text
Keywords: financial,python
Platform: UNKNOWN
Classifier: Development Status :: 3 - Alpha
Classifier: Intended Audience :: Developers
Classifier: Topic :: Software Development :: Build Tools
Classifier: License :: OSI Approved :: MIT License
Classifier: Programming Language :: Python :: 3.6
